bwslib/__init__.py
bwslib/bws_auth.py
bwslib/sseclient.py
bwslib-0.0.1.dist-info/METADATA
bwslib-0.0.1.dist-info/WHEEL
bwslib-0.0.1.dist-info/top_level.txt
bwslib-0.0.1.dist-info/RECORD
