Metadata-Version: 2.1
Name: bwslib
Version: 0.0.1
Summary: BWS auth lib package
Home-page: UNKNOWN
License: UNKNOWN
Platform: UNKNOWN
Classifier: Programming Language :: Python
Classifier: License :: OSI Approved :: MIT License
Classifier: Operating System :: OS Independent
